Workbook

Sheet Summary
A1: APPLE INC. (NASDAQ: AAPL) — Q4 FY2026 EARNINGS FORECAST
A2: Earnings Forecast & Target Price — Equity Research portfolio. Anchored on Apple's own July 30, 2026 guidance.
A3: Reporting date: October 29, 2026 (confirmed, after market close)
A5: Scenario | B5: Revenue | C5: EPS | D5: vs. Street ($1.98)
A6: Bear (low end of guide) | B6: ='Forecast Model'!B27 -> 111.725 | C6: ='Forecast Model'!B32 -> 1.8856292
A7: Base (guidance midpoint) | B7: ='Forecast Model'!C27 -> 112.75 | C7: ='Forecast Model'!C32 -> 1.9537119 | D7: =C7/1.98-1 -> -0.013276836
A8: Bull (high end of guide) | B8: ='Forecast Model'!D27 -> 113.775 | C8: ='Forecast Model'!D32 -> 2.0223783 | D8: =C8/1.98-1 -> 0.021403184
A10: Target Price — Base Case | B10: ='Forecast Model'!B42 -> 325.08945
A11: Target Price — Bull Case | B11: ='Forecast Model'!B43 -> 327.61931
A12: Current Price | B12: ='Forecast Model'!B44 -> 320.9
A13: Implied Upside — Base Case | B13: ='Forecast Model'!B42/'Forecast Model'!B44-1 -> 0.013055323
A15: Key Context Since the Original Forecast
A16: This forecast was revised after discovering Apple's own official Q4 FY2026 guidance (given July 30, 2026): revenue growth of 9-11% YoY, gross margin 47-48%, opex $19.1-19.4bn. The original version of this model used a self-derived 12.5% growth assumption and a Street consensus figure that predated this guidance; anchoring on management's own stated range instead is a materially stronger basis. Separately, Tim Cook stepped down as CEO effective September 1, 2026, succeeded by John Ternus (a 25-year Apple veteran, former SVP of Hardware Engineering) — this was Cook's final earnings call as CEO. A redesigned Siri, reportedly using Google AI technology, is also launching within this quarter. Also relevant: Apple's own “Surprise and Shine” event is September 9, 2026 — the first major product event of the Ternus era, expected to unveil the foldable iPhone; AAPL fell ~2% on September 4 on reports that initial foldable production is limited to a few hundred units/day, a live illustration of the supply constraints already built into the guided range this forecast uses.

Sheet Historicals
A1: APPLE INC. — QUARTERLY TREND, FY2026 (THROUGH Q3)
A2: $ in billions except per-share data. Fiscal year ends the last Saturday of September.
A4: Fiscal Quarter | B4: Q4 FY25A (year-ago) | C4: Q1 FY26A | D4: Q2 FY26A | E4: Q3 FY26A
A5: Total Revenue | B5: 102.5 | C5: 143.8 | D5: 111.2 | E5: 109.4
A6: Revenue Growth % YoY | B6: 0.08 | C6: 0.16 | D6: 0.17 | E6: 0.16
A7: Gross Margin % | B7: n/a | C7: n/a | D7: 0.493 | E7: 0.501
A8: Diluted EPS | B8: 1.85 | C8: 2.84 | D8: 2.01 | E8: 2.02
A9: EPS Growth % YoY | B9: n/a | C9: 0.19 | D9: 0.22 | E9: 0.29
A11: Segment Detail (where disclosed)
A12: iPhone Revenue (Q2 FY26A) | B12: 57.99
A13: Services Revenue (Q2 FY26A) | B13: 30.98
A14: Services Growth % YoY (Q2 FY26A) | B14: 0.163
A16: Market Data (as of Aug 28-29, 2026)
A17: Share Price | B17: 320.9
A18: Diluted Shares Outstanding (bn, approx.) | B18: 14.8
A19: TTM Diluted EPS | B19: 8.71
A20: Current P/E (TTM) | B20: =B17/B19 -> 36.84271
A21: Street Consensus — Q4 FY26E Revenue | B21: 115.06
A22: Street Consensus — Q4 FY26E EPS | B22: 2.01

Sheet Forecast Model
A1: Q4 FY2026 EARNINGS FORECAST — BUILT FROM ACTUAL Q2/Q3 COST STRUCTURE
A2: Reporting date: October 29, 2026 (confirmed, after market close). $ in billions except per-share data.
A4: Step 1: Calibrate the Operating Cost Structure from Real Actuals
A5: Tax Rate (effective) | B5: 0.16
A6: Q2 FY26A: Revenue / Net Income / GM% (inputs) | B6: =Historicals!D5 -> 111.2 | C6: 29.6 | D6: =Historicals!D7 -> 0.493
A7: Q2 implied pre-tax margin | B7: =(C6/(1-B5))/B6 -> 0.31688935
A8: Q2 implied opex % of revenue | B8: =D6-B7 -> 0.17611065
A10: Q3 FY26A: Revenue / EPS / GM% (inputs) | B10: =Historicals!E5 -> 109.4 | C10: =Historicals!E8 -> 2.02 | D10: =Historicals!E7 -> 0.501
A11: Q3 implied Net Income | B11: =C10*Historicals!B18 -> 29.896
A12: Q3 implied pre-tax margin | B12: =(B11/(1-B5))/B10 -> 0.32532428
A13: Q3 implied opex % of revenue | B13: =D10-B12 -> 0.17567572
A14: Calibrated Opex % of Revenue (avg. Q2/Q3) | B14: =AVERAGE(B8,B13) -> 0.17589319
A16: Step 2: Build the Q4 FY2026E Forecast — Anchored on Apple's Own Guidance
A17: Q4 FY2025A Revenue (base) | B17: =Historicals!B5 -> 102.5
A18: Guided Revenue Growth Range (low / high) | B18: 0.09 | C18: 0.11
A19: Guided Gross Margin Range (low / high) | B19: 0.47 | C19: 0.48
A20: Guided Operating Expenses, $bn (low / high) | B20: 19.1 | C20: 19.4
A21: Tax Rate | B21: 0.16
A22: Diluted Shares (bn) | B22: 14.75
A24: Bear / Base / Bull — Built From the Guided Range
A25: Scenario | B25: Bear (9% / 47% / $19.4bn) | C25: Base (10% / 47.5% / $19.25bn) | D25: Bull (11% / 48% / $19.1bn)
A26: Revenue Growth Assumed | B26: 0.09 | C26: 0.1 | D26: 0.11
A27: Revenue | B27: =B17*(1+B26) -> 111.725 | C27: =B17*(1+C26) -> 112.75 | D27: =B17*(1+D26) -> 113.775
A28: Gross Margin Assumed | B28: 0.47 | C28: 0.475 | D28: 0.48
A29: Opex ($bn) Assumed | B29: 19.4 | C29: 19.25 | D29: 19.1
A30: Operating Income | B30: =B27*B28-B29 -> 33.11075 | C30: =C27*C28-C29 -> 34.30625 | D30: =D27*D28-D29 -> 35.512
A31: Net Income | B31: =B30*(1-$B$21) -> 27.81303 | C31: =C30*(1-$B$21) -> 28.81725 | D31: =D30*(1-$B$21) -> 29.83008
A32: Diluted EPS | B32: =B31/$B$22 -> 1.8856292 | C32: =C31/$B$22 -> 1.9537119 | D32: =D31/$B$22 -> 2.0223783
A34: Step 3: Compare to Street Consensus and Set Target Price
A35: Street Consensus EPS (current, 44 analysts) | B35: 1.98
A36: My Base Case EPS vs. Street | B36: =C32/B35-1 -> -0.013276836
A37: My Bull Case EPS vs. Street | B37: =D32/B35-1 -> 0.021403184
A39: FY2026E EPS (Q1A+Q2A+Q3A+Q4E Base) | B39: =Historicals!C8+Historicals!D8+Historicals!E8+C32 -> 8.8237119
A40: FY2026E EPS (Q1A+Q2A+Q3A+Q4E Bull) | B40: =Historicals!C8+Historicals!D8+Historicals!E8+D32 -> 8.8923783
A41: Current P/E (TTM) | B41: =Historicals!B20 -> 36.84271
A42: Target Price — Base Case | B42: =B41*B39 -> 325.08945
A43: Target Price — Bull Case | B43: =B41*B40 -> 327.61931
A44: Current Share Price | B44: =Historicals!B17 -> 320.9
A45: Implied Upside — Base Case | B45: =B42/B44-1 -> 0.013055323
A46: Implied Upside — Bull Case | B46: =B43/B44-1 -> 0.020938956
