Workbook

Sheet Cover
B2: India Banking Sector — Deep-Dive Coverage & Valuation
B3: 15-bank universe, Q1 FY27 results season — explicit BUY/HOLD/SELL ratings via Gordon Growth Model
B5: Universe: | C5: 7 private banks (HDFC, ICICI, Axis, Kotak, IndusInd, Federal, IDFC First) + 8 PSU banks (SBI, PNB, BoB, Canara, Union, Indian Bank, BoI, UCO)
B6: Data as of: | C6: Q1 FY27 results (Jul-Aug 2026 reporting); market data late Aug-early Sep 2026
B8: Contents
B9: Industry Overview | C9: Sector size, credit-deposit gap, and the AQR→IBC→PCA→recapitalization credit cycle
B10: Consolidation & Regulatory | C10: 27→12 PSU mergers, unsecured-lending crackdown, ECL transition, HDFC merger mechanics, UPI scale
B11: Bank Data | C11: Full Q1 FY27 comparable dataset across 15 banks: growth, margins, asset quality, capital, valuation
B12: Valuation Engine | C12: Gordon Growth fair-P/B model → explicit BUY/HOLD/SELL rating per bank
B13: SOTP | C13: Embedded listed-subsidiary value at HDFC Bank, ICICI Bank and SBI
B14: Analysis | C14: Private vs. PSU group averages and the valuation-convergence case
B16: The Debate
B17: Private banks trade at 1.74x average P/B against 0.94x for PSU banks — an 85% premium — even though, across our 15-bank universe, PSU banks post a HIGHER average ROE (16.0% vs 13.0%) and statistically comparable Net NPA. The Valuation Engine tab turns that observation into explicit calls: 3 BUYs (all PSU), 3 SELLs (all private), 1 HOLD, and 8 flagged for insufficient data rather than a forced rating.
B19: Ratings Scoreboard (from Valuation Engine)
B20: Bank | C20: Type | D20: Implied Upside | E20: Rating
B21: ='Valuation Engine'!B18 -> HDFC Bank | C21: ='Valuation Engine'!C18 -> Private | D21: ='Valuation Engine'!I18 -> -0.42719257 | E21: ='Valuation Engine'!J18 -> SELL
B22: ='Valuation Engine'!B19 -> ICICI Bank | C22: ='Valuation Engine'!C19 -> Private | D22: ='Valuation Engine'!I19 -> n.a. | E22: ='Valuation Engine'!J19 -> Insufficient data
B23: ='Valuation Engine'!B20 -> Axis Bank | C23: ='Valuation Engine'!C20 -> Private | D23: ='Valuation Engine'!I20 -> -0.47966819 | E23: ='Valuation Engine'!J20 -> SELL
B24: ='Valuation Engine'!B21 -> Kotak Mahindra Bank | C24: ='Valuation Engine'!C21 -> Private | D24: ='Valuation Engine'!I21 -> -0.67402564 | E24: ='Valuation Engine'!J21 -> SELL
B25: ='Valuation Engine'!B22 -> IndusInd Bank | C25: ='Valuation Engine'!C22 -> Private | D25: ='Valuation Engine'!I22 -> n.a. | E25: ='Valuation Engine'!J22 -> Insufficient data
B26: ='Valuation Engine'!B23 -> Federal Bank | C26: ='Valuation Engine'!C23 -> Private | D26: ='Valuation Engine'!I23 -> n.a. | E26: ='Valuation Engine'!J23 -> Insufficient data
B27: ='Valuation Engine'!B24 -> IDFC First Bank | C27: ='Valuation Engine'!C24 -> Private | D27: ='Valuation Engine'!I24 -> n.a. | E27: ='Valuation Engine'!J24 -> Insufficient data
B28: ='Valuation Engine'!B25 -> SBI | C28: ='Valuation Engine'!C25 -> PSU | D28: ='Valuation Engine'!I25 -> n.a. | E28: ='Valuation Engine'!J25 -> Insufficient data
B29: ='Valuation Engine'!B26 -> PNB | C29: ='Valuation Engine'!C26 -> PSU | D29: ='Valuation Engine'!I26 -> 0.30822281 | E29: ='Valuation Engine'!J26 -> BUY
B30: ='Valuation Engine'!B27 -> Bank of Baroda | C30: ='Valuation Engine'!C27 -> PSU | D30: ='Valuation Engine'!I27 -> 0.4491135 | E30: ='Valuation Engine'!J27 -> BUY
B31: ='Valuation Engine'!B28 -> Canara Bank | C31: ='Valuation Engine'!C28 -> PSU | D31: ='Valuation Engine'!I28 -> 0.26173919 | E31: ='Valuation Engine'!J28 -> BUY
B32: ='Valuation Engine'!B29 -> Union Bank of India | C32: ='Valuation Engine'!C29 -> PSU | D32: ='Valuation Engine'!I29 -> 0.0071887133 | E32: ='Valuation Engine'!J29 -> HOLD
... B35: ='Valuation Engine'!B32 -> UCO Bank | C35: ='Valuation Engine'!C32 -> PSU | D35: ='Valuation Engine'!I32 -> n.a. | E35: ='Valuation Engine'!J32 -> Insufficient data
B37: This is an independent, illustrative sector analysis built for portfolio/interview demonstration purposes using public results and market data. It is not investment advice. See the companion detailed sector report (Word doc) for the full write-up.

Sheet Industry Overview
B2: Industry Overview — Size, Structure & the Credit Cycle
B4: A. Sector Size (FY26)
B5: Scheduled Commercial Banks (SCBs) | C5: ~90+ entities | D5: 12 PSU banks, 21 private banks, ~44 foreign banks, small finance banks (SFBs) and regional rural banks (RRBs) make up the rest.
B6: System-wide credit growth, FY26 | C6: ~11-13% YoY | D6: Broadly tracking nominal GDP growth plus a modest multiplier; moderated from the mid-teens pace seen in FY23-24.
B7: System-wide deposit growth, FY26 | C7: ~9-10% YoY | D7: Persistently running below credit growth — the 'credit-deposit gap' that has forced banks to compete harder (and pay more) for deposits, pressuring NIMs system-wide.
B8: PSU share of system deposits | C8: ~55-60% | D8: PSU banks retain majority share of the deposit franchise (legacy branch density, government business, pension accounts) even as private banks lead on incremental credit growth and profitability.
B10: B. The Credit Cycle: From Crisis to Record Profitability
B11: This is the single most important context for reading any current Indian bank's numbers: the entire sector spent roughly a decade digging out of a corporate-lending NPA crisis, and only fully emerged in the last 2-3 years. A GNPA print of ~1.5-2% today needs to be read against where the same banks stood in FY18.
B12: Year / Period | C12: Event | D12: Why it mattered
B13: 2015-16 | C13: RBI's Asset Quality Review (AQR) | D13: Forced banks to recognize NPAs they had been rolling over or restructuring — gross NPAs across the system roughly doubled on paper almost overnight.
B14: 2016 | C14: Insolvency and Bankruptcy Code (IBC) enacted | D14: Gave banks a real, time-bound legal mechanism to force resolution or liquidation of stressed corporate borrowers — previously recovery could drag on for a decade-plus.
B15: FY18 | C15: System GNPA peaks (~11-12% system-wide; several PSU banks above 15-20%) | D15: The bottom of the cycle. Twin balance sheet problem (over-levered infrastructure/steel corporates + undercapitalized PSU banks) at its worst.
B16: 2017-2021 | C16: 11 PSU banks placed under RBI's Prompt Corrective Action (PCA) framework | D16: Restricted lending, branch expansion and dividend payouts at the weakest PSU banks until capital and asset-quality metrics improved — effectively a supervised recovery program.
B17: 2019-2020 | C17: Government recapitalizes PSU banks (₹recapitalization bonds) + mega-mergers (see Consolidation tab) | D17: Rebuilt capital buffers and consolidated 27 PSU banks into 12, creating fewer, larger, better-capitalized entities.
B18: 2020-2022 | C18: Covid-19 forbearance + one-time restructuring windows | D18: Delayed recognition of some stress but ultimately proved less damaging than feared, given strong systemic liquidity support.
B19: FY23-26 | C19: System GNPA falls to multi-year / multi-decade lows (SBI: 1.47%, a 20-year low) | D19: The cleanup is largely complete. Provision coverage ratios are high (70-75%+ at most large banks), capital ratios are comfortable, and profitability is at record levels across the sector.
B21: Implication for the Private vs. PSU debate (Analysis tab): the current-cycle asset-quality convergence isn't an accident or a one-off good quarter — it's the tail end of a decade-long, policy-driven cleanup (AQR → IBC → PCA → recapitalization → consolidation). That's a structural argument, not just a cyclical one, for why the valuation gap deserves fresh scrutiny — which the Valuation Engine tab then quantifies bank-by-bank.

Sheet Consolidation & Regulatory
B2: PSU Consolidation History & Current Regulatory Watch
B4: A. PSU Bank Consolidation: 27 Banks → 12
B5: Date | C5: Transaction
B6: Apr 2017 | C6: SBI absorbs 5 associate banks (State Bank of Bikaner & Jaipur, Mysore, Travancore, Hyderabad, Patiala) + Bharatiya Mahila Bank
B7: Apr 2019 | C7: Bank of Baroda absorbs Vijaya Bank and Dena Bank
B8: Apr 2020 | C8: Punjab National Bank absorbs Oriental Bank of Commerce + United Bank of India
B9: Apr 2020 | C9: Canara Bank absorbs Syndicate Bank
B10: Apr 2020 | C10: Union Bank of India absorbs Andhra Bank + Corporation Bank
B11: Apr 2020 | C11: Indian Bank absorbs Allahabad Bank
B13: Result: PSU bank count fell from 27 (pre-2017) to 12 today. Market chatter in 2026 (e.g. PL Capital) suggests the government may eventually target a further consolidation toward 6-7 PSU banks, with smaller names (IOB, UCO Bank, Bank of India, Central Bank of India, Bank of Maharashtra, Punjab & Sind Bank) most often cited as candidates — unconfirmed, but worth watching. Note that 3 of this report's 8 PSU names (UCO Bank, Bank of India, and to a lesser extent Indian Bank) sit in exactly this speculative-consolidation-target zone — a real, if hard-to-time, catalyst not captured in the Valuation Engine's Gordon Growth framework. IDBI Bank's privatization (part-owned by LIC and the Government) has also been an active, if slow-moving, process.
B15: B. Regulatory Watch — What's Actually Moving the Sector Right Now
B16: Theme | C16: Detail
B17: Nov 2023: RBI risk-weight action on unsecured credit | C17: RBI raised risk weights by 25 percentage points on consumer unsecured loans, credit cards, and bank lending to NBFCs, deliberately making unsecured retail growth more capital-intensive. Directly contributed to a subsequent slowdown in unsecured retail and microfinance lending through 2024-2025, and real stress at names most exposed to that book — a cautionary tale for how fast a 'clean' retail growth story can turn. IndusInd Bank's elevated 3.25% GNPA in this dataset is a partial echo of this same period's asset-quality issues.
B18: Expected Credit Loss (ECL) provisioning transition | C18: RBI has been moving Indian banks from the current 'incurred loss' provisioning approach (IRAC norms) toward an Ind AS 109 / IFRS 9-style forward-looking Expected Credit Loss framework, in phases. This will likely require higher day-one provisioning at some banks when fully implemented — a capital and earnings consideration still working through the system, not yet fully priced by the market, and most relevant to the thinner-capitalized PSU names in this dataset (UCO Bank, Bank of India).
B19: Basel III capital framework | C19: Indian banks now run comfortably above minimum CET1/capital adequacy requirements post the FY19-21 recapitalization cycle. Within this report's dataset, PNB (CRAR 18.13%), Union Bank (18.46%) and UCO Bank (19.03%) all carry comfortable buffers — a structural change from a decade ago, when several PSU banks were capital-constrained and unable to grow.
B20: HDFC Bank – HDFC Ltd merger (completed Jul 2023) still working through the system | C20: The reverse merger of India's largest mortgage lender into HDFC Bank added a large low-yielding mortgage book funded without a matching deposit franchise, pushing HDFC Bank's loan-to-deposit ratio well above 100% at merger and diluting its best-in-class CASA ratio. HDFC Bank has spent FY24-26 deliberately growing deposits faster than loans to bring this back into balance — a multi-year normalization, and part of why the Valuation Engine flags HDFC Bank as a SELL on current ROE despite its franchise quality: the merger is still diluting return ratios.
B22: C. Digital Disruption — UPI's Scale
B23: FY2025-26 UPI transaction volume | C23: 24,162 crore (~241.6 billion) transactions, up from just 2 crore in FY2016-17
B24: FY2025-26 UPI transaction value | C24: ~₹314 lakh crore (~$3.7 trillion)
B25: Banks live on UPI | C25: 703, up from 44 at launch (FY2016-17)
B26: Top-3 app concentration (PhonePe, Google Pay, Paytm) | C26: ~88-93% of UPI volume — banks are largely distribution partners/back-end rails for non-bank apps, not the customer-facing layer
B28: Why this matters for bank economics: UPI is free (zero MDR on P2P and most P2M volume), which means it has driven massive financial inclusion and transaction banking scale without a matching fee-income stream for banks — the commercial value banks capture is mostly in float, deposit stickiness, and cross-sell data, not direct payments revenue. This is a key reason Indian banks have leaned so heavily on credit cards and personal loans (which do carry fee/interest economics) for retail profitability — the same segment the Nov 2023 RBI risk-weight action targeted.

Sheet Bank Data
B2: India Banking Sector — 15-Bank Comparable Universe (Q1 FY27, quarter ended June 30, 2026)
B4: Bank | C4: Type | D4: NII (₹cr) | E4: NII Gr.% | F4: PAT (₹cr) | G4: PAT Gr.% | H4: NIM % | I4: GNPA % | J4: NNPA % | K4: ROA % | L4: ROE % (disc.) | M4: CRAR % | N4: CET1 % | O4: Mkt Cap (₹cr) | P4: P/E (x) | Q4: P/B (x) | R4: Implied ROE (P/B÷P/E) | S4: Primary ROE (val.)
B5: HDFC Bank | C5: Private | D5: 30200 | E5: 0.11 | F5: 16930 | G5: 0.13 | H5: 0.035 | I5: 0.0117 | J5: 0.0041 | K5: N/A | L5: N/A | M5: N/A | N5: N/A | O5: 1084100 | P5: 13.9 | Q5: 2.05 | R5: =IFERROR(Q5/P5,"N/A") -> 0.14748201 | S5: =IF(ISNUMBER(L5),L5,IF(ISNUMBER(R5),R5,"N/A")) -> 0.14748201
B6: ICICI Bank | C6: Private | D6: N/A | E6: N/A | F6: 14805 | G6: 0.159 | H6: 0.04 | I6: 0.0167 | J6: 0.0035 | K6: 0.0218 | L6: N/A | M6: N/A | N6: N/A | O6: 1024000 | P6: 18.5 | Q6: N/A | R6: =IFERROR(Q6/P6,"N/A") -> N/A | S6: =IF(ISNUMBER(L6),L6,IF(ISNUMBER(R6),R6,"N/A")) -> N/A
B7: Axis Bank | C7: Private | D7: N/A | E7: N/A | F7: 6390 | G7: 0.09 | H7: 0.0391 | I7: 0.0128 | J7: 0.0039 | K7: N/A | L7: N/A | M7: N/A | N7: N/A | O7: 391000 | P7: 13.87 | Q7: 1.8 | R7: =IFERROR(Q7/P7,"N/A") -> 0.1297765 | S7: =IF(ISNUMBER(L7),L7,IF(ISNUMBER(R7),R7,"N/A")) -> 0.1297765
B8: Kotak Mahindra Bank | C8: Private | D8: N/A | E8: N/A | F8: 3900 | G8: 0.18 | H8: N/A | I8: N/A | J8: N/A | K8: N/A | L8: N/A | M8: N/A | N8: N/A | O8: 420000 | P8: 19.16 | Q8: 2.15 | R8: =IFERROR(Q8/P8,"N/A") -> 0.11221294 | S8: =IF(ISNUMBER(L8),L8,IF(ISNUMBER(R8),R8,"N/A")) -> 0.11221294
B9: IndusInd Bank | C9: Private | D9: 4685 | E9: 0.01 | F9: 1037 | G9: 0.72 | H9: 0.0357 | I9: 0.0325 | J9: N/A | K9: N/A | L9: N/A | M9: 0.1715 | N9: N/A | O9: 81665 | P9: N/M | Q9: 1.27 | R9: =IFERROR(Q9/P9,"N/A") -> N/A | S9: N/A
B10: Federal Bank | C10: Private | D10: 2946 | E10: 0.26 | F10: 1177 | G10: 0.37 | H10: N/A | I10: 0.0152 | J10: 0.0018 | K10: N/A | L10: N/A | M10: 0.1697 | N10: N/A | O10: 84485 | P10: 14.8 | Q10: N/A | R10: =IFERROR(Q10/P10,"N/A") -> N/A | S10: =IF(ISNUMBER(L10),L10,IF(ISNUMBER(R10),R10,"N/A")) -> N/A
B11: IDFC First Bank | C11: Private | D11: 5972 | E11: 0.211 | F11: 1075 | G11: 1.324 | H11: 0.0596 | I11: 0.0151 | J11: 0.0044 | K11: 0.0106 | L11: N/A | M11: 0.1505 | N11: 0.1333 | O11: 72650 | P11: 35 | Q11: 1.44 | R11: =IFERROR(Q11/P11,"N/A") -> 0.041142857 | S11: N/A
B12: SBI | C12: PSU | D12: 46992 | E12: 0.1488 | F12: 21121 | G12: 0.1023 | H12: 0.03 | I12: 0.0147 | J12: 0.0038 | K12: N/A | L12: N/A | M12: N/A | N12: N/A | O12: 947500 | P12: 12.19 | Q12: N/A | R12: =IFERROR(Q12/P12,"N/A") -> N/A | S12: =IF(ISNUMBER(L12),L12,IF(ISNUMBER(R12),R12,"N/A")) -> N/A
B13: PNB | C13: PSU | D13: 10798 | E13: 0.021 | F13: 5253 | G13: 2.136 | H13: 0.025 | I13: 0.0278 | J13: 0.0028 | K13: 0.0104 | L13: 0.1733 | M13: 0.1813 | N13: N/A | O13: 132500 | P13: 6.4 | Q13: 1 | R13: =IFERROR(Q13/P13,"N/A") -> 0.15625 | S13: =IF(ISNUMBER(L13),L13,IF(ISNUMBER(R13),R13,"N/A")) -> 0.1733
B14: Bank of Baroda | C14: PSU | D14: 12524 | E14: 0.095 | F14: 1278 | G14: -0.72 | H14: 0.0277 | I14: 0.0199 | J14: 0.005 | K14: 0.0108 | L14: 0.1538 | M14: N/A | N14: N/A | O14: 123400 | P14: 6.98 | Q14: 0.76 | R14: =IFERROR(Q14/P14,"N/A") -> 0.10888252 | S14: =IF(ISNUMBER(L14),L14,IF(ISNUMBER(R14),R14,"N/A")) -> 0.1538
B15: Canara Bank | C15: PSU | D15: 10215 | E15: 0.134 | F15: 4856 | G15: 0.022 | H15: 0.0252 | I15: N/A | J15: N/A | K15: N/A | L15: N/A | M15: N/A | N15: N/A | O15: 114000 | P15: 5.92 | Q15: 1 | R15: =IFERROR(Q15/P15,"N/A") -> 0.16891892 | S15: =IF(ISNUMBER(L15),L15,IF(ISNUMBER(R15),R15,"N/A")) -> 0.16891892
B16: Union Bank of India | C16: PSU | D16: 10037 | E16: 0.101 | F16: 5332 | G16: 0.295 | H16: 0.0276 | I16: 0.0265 | J16: 0.0047 | K16: N/A | L16: N/A | M16: 0.1846 | N16: N/A | O16: 139580 | P16: 6.9 | Q16: 1 | R16: =IFERROR(Q16/P16,"N/A") -> 0.14492754 | S16: =IF(ISNUMBER(L16),L16,IF(ISNUMBER(R16),R16,"N/A")) -> 0.14492754
B17: Indian Bank | C17: PSU | D17: 7435 | E17: 0.17 | F17: N/A | G17: 0.1 | H17: 0.0341 | I17: 0.0186 | J17: 0.0015 | K17: N/A | L17: N/A | M17: N/A | N17: N/A | O17: 114000 | P17: 10.42 | Q17: N/A | R17: =IFERROR(Q17/P17,"N/A") -> N/A | S17: =IF(ISNUMBER(L17),L17,IF(ISNUMBER(R17),R17,"N/A")) -> N/A
B18: Bank of India | C18: PSU | D18: 6833 | E18: 0.1261 | F18: 3068 | G18: 0.36 | H18: N/A | I18: N/A | J18: N/A | K18: N/A | L18: N/A | M18: N/A | N18: N/A | O18: 64900 | P18: 6.71 | Q18: N/A | R18: =IFERROR(Q18/P18,"N/A") -> N/A | S18: =IF(ISNUMBER(L18),L18,IF(ISNUMBER(R18),R18,"N/A")) -> N/A
B19: UCO Bank | C19: PSU | D19: N/A | E19: N/A | F19: 656 | G19: 0.08 | H19: 0.0305 | I19: 0.0208 | J19: 0.0025 | K19: N/A | L19: N/A | M19: 0.1903 | N19: N/A | O19: 36700 | P19: 15.48 | Q19: N/A | R19: =IFERROR(Q19/P19,"N/A") -> N/A | S19: =IF(ISNUMBER(L19),L19,IF(ISNUMBER(R19),R19,"N/A")) -> N/A
B21: Column R (Implied ROE) uses the identity ROE = EPS/BVPS = (Price÷BVPS)/(Price÷EPS) = P/B ÷ P/E — a standard cross-check wherever a bank doesn't separately disclose ROE. Column S prefers the company-disclosed ROE where available (PNB, Bank of Baroda) since one-off items can distort the P/E-derived figure (see Bank of Baroda comment); it falls back to the implied ROE otherwise. This Primary ROE feeds the Valuation Engine tab.
B22: Cells marked N/A were not independently verified within this research pass. All figures sourced from company results releases, exchange filings, and named market-data providers as of the dates in each cell's comment.

Sheet Valuation Engine
B2: Gordon Growth Valuation Engine — Fair P/B, Implied Upside & Rating
B4: A. Model Assumptions
B5: Risk-free rate (India 10Y G-Sec) | C5: 0.0695
B6: Equity risk premium (India, assumed) | C6: 0.065
B7: Beta — private banks (assumed) | C7: 1
B8: Beta — PSU banks (assumed, higher risk) | C8: 1.15
B9: Cost of equity — private banks (Rf + β×ERP) | C9: =C5+C7*C6 -> 0.1345
B10: Cost of equity — PSU banks (Rf + β×ERP) | C10: =C5+C8*C6 -> 0.14425
B11: Sustainable growth (g) — private banks (assumed) | C11: 0.06
B12: Sustainable growth (g) — PSU banks (assumed) | C12: 0.05
B14: Gordon Growth (Fair P/B) model: Fair P/B = (ROE − g) / (Ke − g). This is the standard bank-sector valuation framework (used in place of DCF/EV-EBITDA, which don't fit deposit-taking institutions) — it directly links a bank's sustainable ROE to the book multiple it deserves. All Rf/ERP/Beta/g inputs above are editable assumptions (yellow cells); ratings will re-flex automatically.
B16: B. Per-Bank Valuation
B17: Bank | C17: Type | D17: Primary ROE | E17: Ke | F17: g | G17: Fair P/B | H17: Current P/B | I17: Implied Upside/(Downside) | J17: Rating
B18: HDFC Bank | C18: ='Bank Data'!C5 -> Private | D18: ='Bank Data'!S5 -> 0.14748201 | E18: =IF(C18="Private",$C$9,$C$10) -> 0.1345 | F18: =IF(C18="Private",$C$11,$C$12) -> 0.06 | G18: =IFERROR((D18-F18)/(E18-F18),"n.a.") -> 1.1742552 | H18: ='Bank Data'!Q5 -> 2.05 | I18: =IFERROR(G18/H18-1,"n.a.") -> -0.42719257 | J18: =IF(OR(ISTEXT(G18),ISTEXT(H18)),"Insufficient data",IF(I18>=0.15,"BUY",IF(I18<=-0.1,"SELL","HOLD"))) -> SELL
B19: ICICI Bank | C19: ='Bank Data'!C6 -> Private | D19: ='Bank Data'!S6 -> N/A | E19: =IF(C19="Private",$C$9,$C$10) -> 0.1345 | F19: =IF(C19="Private",$C$11,$C$12) -> 0.06 | G19: =IFERROR((D19-F19)/(E19-F19),"n.a.") -> n.a. | H19: ='Bank Data'!Q6 -> N/A | I19: =IFERROR(G19/H19-1,"n.a.") -> n.a. | J19: =IF(OR(ISTEXT(G19),ISTEXT(H19)),"Insufficient data",IF(I19>=0.15,"BUY",IF(I19<=-0.1,"SELL","HOLD"))) -> Insufficient data
B20: Axis Bank | C20: ='Bank Data'!C7 -> Private | D20: ='Bank Data'!S7 -> 0.1297765 | E20: =IF(C20="Private",$C$9,$C$10) -> 0.1345 | F20: =IF(C20="Private",$C$11,$C$12) -> 0.06 | G20: =IFERROR((D20-F20)/(E20-F20),"n.a.") -> 0.93659726 | H20: ='Bank Data'!Q7 -> 1.8 | I20: =IFERROR(G20/H20-1,"n.a.") -> -0.47966819 | J20: =IF(OR(ISTEXT(G20),ISTEXT(H20)),"Insufficient data",IF(I20>=0.15,"BUY",IF(I20<=-0.1,"SELL","HOLD"))) -> SELL
B21: Kotak Mahindra Bank | C21: ='Bank Data'!C8 -> Private | D21: ='Bank Data'!S8 -> 0.11221294 | E21: =IF(C21="Private",$C$9,$C$10) -> 0.1345 | F21: =IF(C21="Private",$C$11,$C$12) -> 0.06 | G21: =IFERROR((D21-F21)/(E21-F21),"n.a.") -> 0.70084488 | H21: ='Bank Data'!Q8 -> 2.15 | I21: =IFERROR(G21/H21-1,"n.a.") -> -0.67402564 | J21: =IF(OR(ISTEXT(G21),ISTEXT(H21)),"Insufficient data",IF(I21>=0.15,"BUY",IF(I21<=-0.1,"SELL","HOLD"))) -> SELL
B22: IndusInd Bank | C22: ='Bank Data'!C9 -> Private | D22: ='Bank Data'!S9 -> N/A | E22: =IF(C22="Private",$C$9,$C$10) -> 0.1345 | F22: =IF(C22="Private",$C$11,$C$12) -> 0.06 | G22: =IFERROR((D22-F22)/(E22-F22),"n.a.") -> n.a. | H22: ='Bank Data'!Q9 -> 1.27 | I22: =IFERROR(G22/H22-1,"n.a.") -> n.a. | J22: =IF(OR(ISTEXT(G22),ISTEXT(H22)),"Insufficient data",IF(I22>=0.15,"BUY",IF(I22<=-0.1,"SELL","HOLD"))) -> Insufficient data
B23: Federal Bank | C23: ='Bank Data'!C10 -> Private | D23: ='Bank Data'!S10 -> N/A | E23: =IF(C23="Private",$C$9,$C$10) -> 0.1345 | F23: =IF(C23="Private",$C$11,$C$12) -> 0.06 | G23: =IFERROR((D23-F23)/(E23-F23),"n.a.") -> n.a. | H23: ='Bank Data'!Q10 -> N/A | I23: =IFERROR(G23/H23-1,"n.a.") -> n.a. | J23: =IF(OR(ISTEXT(G23),ISTEXT(H23)),"Insufficient data",IF(I23>=0.15,"BUY",IF(I23<=-0.1,"SELL","HOLD"))) -> Insufficient data
B24: IDFC First Bank | C24: ='Bank Data'!C11 -> Private | D24: ='Bank Data'!S11 -> N/A | E24: =IF(C24="Private",$C$9,$C$10) -> 0.1345 | F24: =IF(C24="Private",$C$11,$C$12) -> 0.06 | G24: =IFERROR((D24-F24)/(E24-F24),"n.a.") -> n.a. | H24: ='Bank Data'!Q11 -> 1.44 | I24: =IFERROR(G24/H24-1,"n.a.") -> n.a. | J24: =IF(OR(ISTEXT(G24),ISTEXT(H24)),"Insufficient data",IF(I24>=0.15,"BUY",IF(I24<=-0.1,"SELL","HOLD"))) -> Insufficient data
B25: SBI | C25: ='Bank Data'!C12 -> PSU | D25: ='Bank Data'!S12 -> N/A | E25: =IF(C25="Private",$C$9,$C$10) -> 0.14425 | F25: =IF(C25="Private",$C$11,$C$12) -> 0.05 | G25: =IFERROR((D25-F25)/(E25-F25),"n.a.") -> n.a. | H25: ='Bank Data'!Q12 -> N/A | I25: =IFERROR(G25/H25-1,"n.a.") -> n.a. | J25: =IF(OR(ISTEXT(G25),ISTEXT(H25)),"Insufficient data",IF(I25>=0.15,"BUY",IF(I25<=-0.1,"SELL","HOLD"))) -> Insufficient data
B26: PNB | C26: ='Bank Data'!C13 -> PSU | D26: ='Bank Data'!S13 -> 0.1733 | E26: =IF(C26="Private",$C$9,$C$10) -> 0.14425 | F26: =IF(C26="Private",$C$11,$C$12) -> 0.05 | G26: =IFERROR((D26-F26)/(E26-F26),"n.a.") -> 1.3082228 | H26: ='Bank Data'!Q13 -> 1 | I26: =IFERROR(G26/H26-1,"n.a.") -> 0.30822281 | J26: =IF(OR(ISTEXT(G26),ISTEXT(H26)),"Insufficient data",IF(I26>=0.15,"BUY",IF(I26<=-0.1,"SELL","HOLD"))) -> BUY
B27: Bank of Baroda | C27: ='Bank Data'!C14 -> PSU | D27: ='Bank Data'!S14 -> 0.1538 | E27: =IF(C27="Private",$C$9,$C$10) -> 0.14425 | F27: =IF(C27="Private",$C$11,$C$12) -> 0.05 | G27: =IFERROR((D27-F27)/(E27-F27),"n.a.") -> 1.1013263 | H27: ='Bank Data'!Q14 -> 0.76 | I27: =IFERROR(G27/H27-1,"n.a.") -> 0.4491135 | J27: =IF(OR(ISTEXT(G27),ISTEXT(H27)),"Insufficient data",IF(I27>=0.15,"BUY",IF(I27<=-0.1,"SELL","HOLD"))) -> BUY
B28: Canara Bank | C28: ='Bank Data'!C15 -> PSU | D28: ='Bank Data'!S15 -> 0.16891892 | E28: =IF(C28="Private",$C$9,$C$10) -> 0.14425 | F28: =IF(C28="Private",$C$11,$C$12) -> 0.05 | G28: =IFERROR((D28-F28)/(E28-F28),"n.a.") -> 1.2617392 | H28: ='Bank Data'!Q15 -> 1 | I28: =IFERROR(G28/H28-1,"n.a.") -> 0.26173919 | J28: =IF(OR(ISTEXT(G28),ISTEXT(H28)),"Insufficient data",IF(I28>=0.15,"BUY",IF(I28<=-0.1,"SELL","HOLD"))) -> BUY
B29: Union Bank of India | C29: ='Bank Data'!C16 -> PSU | D29: ='Bank Data'!S16 -> 0.14492754 | E29: =IF(C29="Private",$C$9,$C$10) -> 0.14425 | F29: =IF(C29="Private",$C$11,$C$12) -> 0.05 | G29: =IFERROR((D29-F29)/(E29-F29),"n.a.") -> 1.0071887 | H29: ='Bank Data'!Q16 -> 1 | I29: =IFERROR(G29/H29-1,"n.a.") -> 0.0071887133 | J29: =IF(OR(ISTEXT(G29),ISTEXT(H29)),"Insufficient data",IF(I29>=0.15,"BUY",IF(I29<=-0.1,"SELL","HOLD"))) -> HOLD
... B32: UCO Bank | C32: ='Bank Data'!C19 -> PSU | D32: ='Bank Data'!S19 -> N/A | E32: =IF(C32="Private",$C$9,$C$10) -> 0.14425 | F32: =IF(C32="Private",$C$11,$C$12) -> 0.05 | G32: =IFERROR((D32-F32)/(E32-F32),"n.a.") -> n.a. | H32: ='Bank Data'!Q19 -> N/A | I32: =IFERROR(G32/H32-1,"n.a.") -> n.a. | J32: =IF(OR(ISTEXT(G32),ISTEXT(H32)),"Insufficient data",IF(I32>=0.15,"BUY",IF(I32<=-0.1,"SELL","HOLD"))) -> Insufficient data
B34: Rating bands: BUY if Fair P/B implies ≥15% upside to current P/B; SELL if ≤10% downside; HOLD in between. 'Insufficient data' applies where P/B or a usable ROE basis wasn't independently confirmed (see Bank Data tab) — treat these as 'needs primary diligence,' not as a neutral call. This is a book-value re-rating framework, not a price target on its own — pair it with the qualitative read in the companion report before acting on any single rating.

Sheet SOTP
B2: Sum-of-the-Parts — Embedded Subsidiary Value at the 3 Banks With Listed Arms
B4: HDFC Bank, ICICI Bank and SBI all own meaningful stakes in separately listed insurance, asset-management, broking and cards subsidiaries. A pure standalone-bank P/B or P/E multiple misses this embedded value. Subsidiary market caps below are approximate (derived from share price × an estimated/recalled share count where an exact figure wasn't independently confirmed this pass) — treat the attributable-value column as directionally right, not audit-grade precise.
B6: HDFC Bank
B7: Subsidiary | C7: Sub. Mkt Cap (₹cr) | D7: Parent Stake % | E7: Attributable Value (₹cr) | F7: Note
B8: HDFC Life Insurance | C8: 118000 | D8: 0.5 | E8: =IFERROR(C8*D8,"N/A") -> 59000 | F8: Life insurer; HDFC Bank's stake ~50% post multiple secondary stake sales over 2022-24.
B9: HDFC Asset Management Co. | C9: N/A | D9: N/A | E9: =IFERROR(C9*D9,"N/A") -> N/A | F9: Listed AMC; standalone market cap not independently confirmed this pass — excluded from the total below rather than estimated.
B10: Total attributable subsidiary value | E10: =SUM(E8:E9) -> 59000
B11: HDFC Bank standalone market cap (₹cr) | C11: ='Bank Data'!O5 -> 1084100
B12: Subsidiary value as % of parent's own market cap | C12: =E10/C11 -> 0.054423024
B14: ICICI Bank
B15: Subsidiary | C15: Sub. Mkt Cap (₹cr) | D15: Parent Stake % | E15: Attributable Value (₹cr) | F15: Note
B16: ICICI Prudential Life Insurance | C16: 75000 | D16: 0.514 | E16: =IFERROR(C16*D16,"N/A") -> 38550 | F16: Life insurer; ICICI Bank's stake ~51.4%. Subsidiary market cap approximated from recent share price × est. share count — flagged as directional.
B17: ICICI Lombard General Insurance | C17: 83000 | D17: 0.481 | E17: =IFERROR(C17*D17,"N/A") -> 39923 | F17: General insurer; ICICI Bank's stake ~48.1%. Subsidiary market cap approximated — flagged as directional.
B18: Total attributable subsidiary value | E18: =SUM(E16:E17) -> 78473
B19: ICICI Bank standalone market cap (₹cr) | C19: ='Bank Data'!O6 -> 1024000
B20: Subsidiary value as % of parent's own market cap | C20: =E18/C19 -> 0.076633789
B22: SBI
B23: Subsidiary | C23: Sub. Mkt Cap (₹cr) | D23: Parent Stake % | E23: Attributable Value (₹cr) | F23: Note
B24: SBI Life Insurance | C24: 188000 | D24: 0.554 | E24: =IFERROR(C24*D24,"N/A") -> 104152 | F24: Life insurer; SBI's stake ~55.4%. Subsidiary market cap approximated from recent share price × est. share count — flagged as directional.
B25: SBI Cards & Payment Services | C25: 59000 | D25: 0.686 | E25: =IFERROR(C25*D25,"N/A") -> 40474 | F25: Credit card issuer; SBI's stake ~68.6%. Subsidiary market cap approximated — flagged as directional.
B26: SBI Mutual Fund | C26: N/A | D26: N/A | E26: =IFERROR(C26*D26,"N/A") -> N/A | F26: India's largest AMC by AUM; unlisted — not independently valued this pass, but is a further source of unrecognized value beyond the two lines above.
B27: Total attributable subsidiary value | E27: =SUM(E24:E26) -> 144626
B28: SBI standalone market cap (₹cr) | C28: ='Bank Data'!O12 -> 947500
B29: Subsidiary value as % of parent's own market cap | C29: =E27/C28 -> 0.15263958
B31: Read-through: even on approximate figures, HDFC Bank's and SBI's listed-subsidiary stakes each represent a meaningful slice of the parent's own market cap — a reminder that a standalone P/B or P/E comparison (as used in the Valuation Engine tab) is necessarily incomplete for these three names. A rigorous SOTP would net this out before comparing 'core bank' multiples across the peer set; this tab is a directional flag for that adjustment, not a substitute for it.

Sheet Analysis
B2: Private vs. PSU Banks — The Convergence Trade (15-Bank Universe)
B4: A. Group Averages: 7 Private vs. 8 PSU Banks
B5: Metric | C5: Private Avg | D5: PSU Avg
B6: PAT growth, % YoY (reported) | C6: =AVERAGEIF('Bank Data'!$C$5:$C$19,"Private",'Bank Data'!$G$5:$G$19) -> 0.42471429 | D6: =AVERAGEIF('Bank Data'!$C$5:$C$19,"PSU",'Bank Data'!$G$5:$G$19) -> 0.2969125
B7: ⚠ skewed by one-offs — see note
B8: Net Interest Margin, % | C8: =AVERAGEIF('Bank Data'!$C$5:$C$19,"Private",'Bank Data'!$H$5:$H$19) -> 0.04188 | D8: =AVERAGEIF('Bank Data'!$C$5:$C$19,"PSU",'Bank Data'!$H$5:$H$19) -> 0.028585714
B9: Gross NPA, % | C9: =AVERAGEIF('Bank Data'!$C$5:$C$19,"Private",'Bank Data'!$I$5:$I$19) -> 0.017333333 | D9: =AVERAGEIF('Bank Data'!$C$5:$C$19,"PSU",'Bank Data'!$I$5:$I$19) -> 0.021383333
B10: Net NPA, % | C10: =AVERAGEIF('Bank Data'!$C$5:$C$19,"Private",'Bank Data'!$J$5:$J$19) -> 0.00354 | D10: =AVERAGEIF('Bank Data'!$C$5:$C$19,"PSU",'Bank Data'!$J$5:$J$19) -> 0.0033833333
B11: P/E (TTM) | C11: =AVERAGEIF('Bank Data'!$C$5:$C$19,"Private",'Bank Data'!$P$5:$P$19) -> 19.205 | D11: =AVERAGEIF('Bank Data'!$C$5:$C$19,"PSU",'Bank Data'!$P$5:$P$19) -> 8.875
B12: P/B | C12: =AVERAGEIF('Bank Data'!$C$5:$C$19,"Private",'Bank Data'!$Q$5:$Q$19) -> 1.742 | D12: =AVERAGEIF('Bank Data'!$C$5:$C$19,"PSU",'Bank Data'!$Q$5:$Q$19) -> 0.94
B13: Primary ROE (disclosed or implied) | C13: =AVERAGEIF('Bank Data'!$C$5:$C$19,"Private",'Bank Data'!$S$5:$S$19) -> 0.12982382 | D13: =AVERAGEIF('Bank Data'!$C$5:$C$19,"PSU",'Bank Data'!$S$5:$S$19) -> 0.16023661
B15: P/B premium: Private vs. PSU | C15: =C12/D12-1 -> 0.85319149
B17: Averages use AVERAGEIF, which automatically skips 'N/A' text cells — group averages reflect only the banks with confirmed data for that metric (see Bank Data tab for exact coverage per row). The PSU PAT-growth average is heavily distorted by two one-off items this quarter — PNB's +213.6% reflects a low prior-year provisioning base, and Bank of Baroda's reported -72% reflects a one-time ₹5,680cr litigation settlement (normalized BoB PAT was actually +22%) — read individual bank figures on the Bank Data tab, not this average, for growth comparisons.
B19: B. Is the Premium Justified? (Quality-Adjusted View)
B20: GNPA gap (PSU minus Private, pp) | C20: =(D9-C9)*100 -> 0.405
B21: NNPA gap (PSU minus Private, pp) | C21: =(D10-C10)*100 -> -0.015666667
B22: ROE gap (Private minus PSU, pp) | C22: =(C13-D13)*100 -> -3.0412796
B23: P/B gap (Private minus PSU, x) | C23: =C12-D12 -> 0.802
B25: C. Ratings Scoreboard (from Valuation Engine tab)
B26: BUY count | C26: =COUNTIF('Valuation Engine'!$J$18:$J$32,"BUY") -> 3
B27: HOLD count | C27: =COUNTIF('Valuation Engine'!$J$18:$J$32,"HOLD") -> 1
B28: SELL count | C28: =COUNTIF('Valuation Engine'!$J$18:$J$32,"SELL") -> 3
B29: Insufficient data count | C29: =COUNTIF('Valuation Engine'!$J$18:$J$32,"Insufficient data") -> 8
B31: Read together with the GNPA/NNPA gaps above: the asset-quality convergence between the two groups is real and, on Net NPA, essentially complete. The ratings scoreboard shows this isn't a call to buy every PSU bank or sell every private bank — it's concentrated in specific names (see Valuation Engine tab) where current ROE genuinely doesn't support the multiple, in either direction.
