Workbook

Sheet Cover
B2: Jio Platforms Limited — IPO Valuation Analysis
B3: Comparable Company Analysis, based on DRHP filed June 19, 2026
B5: DRHP filing date: | C5: June 19, 2026
B6: Fresh issue size: | C6: Up to 270,000,000 Equity Shares (₹10 FV); no OFS
B7: Promoter: | C7: Reliance Industries Limited
B8: Use of proceeds: | C8: Up to ₹275,000mm RJIL debt prepayment + general corp. purposes (cap 25% of gross proceeds)
B10: Headline Numbers (FY2026A, Restated Consolidated)
B12: ='DRHP Financials'!E5 -> 1468853 | C12: ='DRHP Financials'!E6 -> 762554 | D12: ='DRHP Financials'!E7 -> 0.5191493 | E12: ='DRHP Financials'!E11 -> 300491 | F12: ='DRHP Financials'!E20 -> 524.4 | G12: ='DRHP Financials'!E14 -> 0.36166881
B13: Revenue (FY26) | C13: EBITDA (FY26) | D13: EBITDA Margin | E13: PAT (FY26) | F13: Total Customers | G13: Net Leverage
B15: Valuation Summary — Implied Price Band (from Valuation tab)
B16: Scenario | C16: EV/EBITDA | D16: Implied EV ($bn) | E16: Implied Issue Price (₹) | F16: Post-Money Mkt Cap ($bn)
B17: Bear (telco-only) | C17: ='Valuation & Price Band'!C6 -> 11.932289 | D17: ='Valuation & Price Band'!C16 -> 95.945741 | E17: ='Valuation & Price Band'!C21 -> 987.46708 | F17: ='Valuation & Price Band'!C27 -> 95.848985
B18: Base (blended) | C18: ='Valuation & Price Band'!C7 -> 16 | D18: ='Valuation & Price Band'!D16 -> 128.6536 | E18: ='Valuation & Price Band'!D21 -> 1334.6162 | F18: ='Valuation & Price Band'!D27 -> 129.54519
B19: Bull (platform premium) | C19: ='Valuation & Price Band'!C8 -> 21 | D19: ='Valuation & Price Band'!E16 -> 168.85785 | E19: ='Valuation & Price Band'!E21 -> 1761.3294 | F19: ='Valuation & Price Band'!E27 -> 170.96432
B21: This is an independent, illustrative valuation built from Jio Platforms' DRHP-disclosed financials (Restated Consolidated Financial Information, FY2024-FY2026) and public market data for listed peers. It is not a solicitation, recommendation, or a substitute for the Company's own 'Basis for Issue Price' disclosures, which will be finalized only once the price band is announced. Figures in ₹ million unless stated; USD conversion at ₹94.835/$ (DRHP FY26 FEDAI/FBIL reference rate).

Sheet DRHP Financials
B2: Jio Platforms Limited — Restated Consolidated Financials (from DRHP)
B4: Particulars | C4: FY2024 | D4: FY2025 | E4: FY2026
B5: Revenue from Operations | C5: 1095581 | D5: 1282184 | E5: 1468853
B6: EBITDA | C6: 549587 | D6: 641700 | E6: 762554
B7: EBITDA Margin | C7: =C6/C5 -> 0.50163977 | D7: =D6/D5 -> 0.50047419 | E7: =E6/E5 -> 0.5191493
B8: EBIT | C8: 328556 | D8: 400324 | E8: 490065
B9: EBIT Margin | C9: =C8/C5 -> 0.29989202 | D9: =D8/D5 -> 0.3122204 | E9: =E8/E5 -> 0.33363788
B10: Profit Before Tax | C10: 288080 | D10: 351273 | E10: 403531
B11: Profit After Tax (PAT) | C11: 214232 | D11: 261090 | E11: 300491
B12: PAT Margin | C12: =C11/C5 -> 0.19554191 | D12: =D11/D5 -> 0.20362912 | E12: =E11/E5 -> 0.20457527
B13: Net Debt | C13: 484400 | D13: 452734 | E13: 275792
B14: Net Leverage (Net Debt / EBITDA) | C14: =C13/C6 -> 0.88138912 | D14: =D13/D6 -> 0.70552283 | E14: =E13/E6 -> 0.36166881
B15: Basic EPS (₹) | C15: 23.96 | D15: 29.21 | E15: 33.63
B16: Net Asset Value per Share (₹) | C16: 310.85 | D16: 340.11 | E16: 373.66
B17: Return on Average Net Worth | C17: 0.0802 | D17: 0.0897 | E17: 0.0942
B19: Operating KPIs
B20: Total Customer Base (mm) | C20: 481.8 | D20: 488.2 | E20: 524.4
B21: ARPU, exit quarter (₹/month) | C21: 181.7 | D21: 206.2 | E21: 214
B23: Implied Share Count & Per-Share Metrics
B24: Pre-issue diluted shares outstanding (mm) | E24: =E11/E15 -> 8935.2067
B25: Back-solved as FY26 PAT ÷ FY26 Basic EPS (DRHP does not separately disclose the exact pre-issue share count in the extracted sections). Used as the basis for all per-share valuation math on the Valuation tab.
B26: Fresh issue size (Equity Shares, mm) | E26: 270
B27: USD/INR reference rate | E27: 94.835
B28: Debt prepayment from Net Proceeds (₹mm) | E28: 275000
B30: Revenue CAGR, FY24–FY26 | E30: =(E5/C5)^(1/2)-1 -> 0.15788898
B31: EBITDA CAGR, FY24–FY26 | E31: =(E6/C6)^(1/2)-1 -> 0.17792347
B32: PAT CAGR, FY24–FY26 | E32: =(E11/C11)^(1/2)-1 -> 0.18433227
B34: All figures sourced from Jio Platforms Limited's Draft Red Herring Prospectus dated June 19, 2026 (Restated Consolidated Financial Information and Key Performance Indicators sections), unless individually cited. ₹ in millions unless stated.

Sheet Peer Comps
B2: Listed Telecom Peer Comparison
B4: A. Peer KPIs, FY2026 (as disclosed in Jio's own DRHP comp table, p.123-124)
B5: Particulars ($mm unless %) | C5: Jio Platforms | D5: Bharti Airtel (Consol.) | E5: Bharti Airtel (India ex-Passive Infra) | F5: Vodafone Idea (Consol.)
B6: Revenue from Operations (₹mm) | C6: 1468853 | D6: 2109728 | E6: 1403734 | F6: 448730
B7: EBITDA (₹mm) | C7: 762554 | D7: 1212676 | E7: 821926 | F7: 190040
B8: EBITDA Margin | C8: 0.5191 | D8: 0.5748 | E8: 0.5855 | F8: 0.4235
B9: EBIT (₹mm) | C9: 490065 | D9: 680996 | E9: 426248 | F9: -31040
B10: PAT (₹mm) | C10: 300491 | D10: 338228 | E10: NA | F10: 345520
B11: Net Leverage (Net Debt/EBITDA) | C11: 0.36 | D11: 1.36 | E11: NA | F11: NA
B12: Total Customer Base (mm) | C12: 524.4 | D12: 666 | E12: 482.4 | F12: 192.8
B14: B. Listed Peer Market Data (public market pricing, Aug 2026)
B15: Particulars | C15: Bharti Airtel | D15: Vodafone Idea
B16: Share price (₹) | C16: 1941.3 | D16: NA
B17: Market capitalization (₹mm) | C17: 12144015 | D17: NA
B18: Enterprise value (₹mm) | C18: 14470000 | D18: NA
B19: EV / EBITDA (FY26, on DRHP-comparable EBITDA) | C19: =C18/D7 -> 11.932289 | D19: NA
B20: P/E (trailing, FY26) | C20: =C17/D10 -> 35.904819 | D20: NA
B22: Vodafone Idea shown for completeness (DRHP KPI comparability only): negative EBIT, no stable EV/EBITDA anchor given ongoing financial distress — not used as a valuation multiple reference. Bharti Airtel (Consolidated) is the primary listed-peer multiple anchor; its 'India ex-Passive Infra' cut is structurally closer to Jio's core telecom business (excludes the lower-multiple Indus Towers passive infrastructure business now consolidated into Airtel) but has no separately listed market price, so it is shown for KPI/margin comparison only.

Sheet Valuation & Price Band
B2: Jio Platforms Limited — Implied Valuation & IPO Price Band
B4: A. EV/EBITDA Multiple Scenarios
B5: Scenario | C5: EV/EBITDA | D5: Basis
B6: Bear — telco-only (Bharti Airtel consolidated multiple, no premium) | C6: ='Peer Comps'!C19 -> 11.932289 | D6: (listed peer EV/EBITDA, unadjusted)
B7: Base — blended (telco anchor + moderate platform premium) | C7: 16
B8: Bull — platform premium (street 'peak' scenarios) | C8: 21
B10: Why Jio is unlikely to price like a pure telco: Jio's own DRHP frames the business as a digital connectivity + digital-services platform (AI, cloud, enterprise digital, MyJio app ecosystem), not a commodity carrier. Reported banker/analyst valuations of $123-180bn imply EV/EBITDA of ~15-22x on FY26A EBITDA — roughly 1.3-1.9x Bharti Airtel's ~12x — a scarcity/platform premium consistent with India's largest-ever IPO.
B12: B. Implied Valuation, Issue Price & Proceeds
B13: Scenario | C13: Bear | D13: Base | E13: Bull
B14: FY26A EBITDA (₹mm) | C14: ='DRHP Financials'!$E$6 -> 762554 | D14: ='DRHP Financials'!$E$6 -> 762554 | E14: ='DRHP Financials'!$E$6 -> 762554
B15: Implied Enterprise Value (₹mm) | C15: =C14*$C$6 -> 9099014.4 | D15: =D14*$C$7 -> 12200864 | E15: =E14*$C$8 -> 16013634
B16: Implied Enterprise Value ($bn) | C16: =C15/'DRHP Financials'!$E$27/1000 -> 95.945741 | D16: =D15/'DRHP Financials'!$E$27/1000 -> 128.6536 | E16: =E15/'DRHP Financials'!$E$27/1000 -> 168.85785
B18: Less: FY26A Net Debt (₹mm) | C18: =-'DRHP Financials'!$E$13 -> -275792 | D18: =-'DRHP Financials'!$E$13 -> -275792 | E18: =-'DRHP Financials'!$E$13 -> -275792
B19: Pre-Money Equity Value (₹mm) | C19: =C15+C18 -> 8823222.4 | D19: =D15+D18 -> 11925072 | E19: =E15+E18 -> 15737842
B20: ÷ Pre-issue diluted shares (mm) | C20: ='DRHP Financials'!$E$24 -> 8935.2067 | D20: ='DRHP Financials'!$E$24 -> 8935.2067 | E20: ='DRHP Financials'!$E$24 -> 8935.2067
B21: Implied Issue Price (₹/share) | C21: =C19/C20 -> 987.46708 | D21: =D19/D20 -> 1334.6162 | E21: =E19/E20 -> 1761.3294
B23: Fresh issue proceeds (₹mm) = Price × 270mm shares | C23: =C21*'DRHP Financials'!$E$26 -> 266616.11 | D23: =D21*'DRHP Financials'!$E$26 -> 360346.39 | E23: =E21*'DRHP Financials'!$E$26 -> 475558.93
B24: Fresh issue proceeds ($bn) | C24: =C23/'DRHP Financials'!$E$27/1000 -> 2.8113683 | D24: =D23/'DRHP Financials'!$E$27/1000 -> 3.7997194 | E24: =E23/'DRHP Financials'!$E$27/1000 -> 5.0145931
B26: Post-Money Market Cap (₹mm) | C26: =C19+C23 -> 9089838.5 | D26: =D19+D23 -> 12285418 | E26: =E19+E23 -> 16213401
B27: Post-Money Market Cap ($bn) | C27: =C26/'DRHP Financials'!$E$27/1000 -> 95.848985 | D27: =D26/'DRHP Financials'!$E$27/1000 -> 129.54519 | E27: =E26/'DRHP Financials'!$E$27/1000 -> 170.96432
B29: C. Sanity Checks vs. Peers & Street Estimates
B30: Implied EV/EBITDA (post-money, FY26A) | C30: =C26/C14 -> 11.920255 | D30: =D26/D14 -> 16.110883 | E30: =E26/E14 -> 21.261971
B31: vs. Bharti Airtel EV/EBITDA | C31: ='Peer Comps'!C19 -> 11.932289 | D31: ='Peer Comps'!C19 -> 11.932289 | E31: ='Peer Comps'!C19 -> 11.932289
B32: Implied P/E (post-money, FY26A PAT) | C32: =C26/'DRHP Financials'!$E$11 -> 30.249953 | D32: =D26/'DRHP Financials'!$E$11 -> 40.88448 | E32: =E26/'DRHP Financials'!$E$11 -> 53.956361
B33: vs. Bharti Airtel P/E | C33: ='Peer Comps'!C20 -> 35.904819 | D33: ='Peer Comps'!C20 -> 35.904819 | E33: ='Peer Comps'!C20 -> 35.904819
B35: Street analyst EV range referenced (independent, not this model)
B36: Goldman Sachs: bear $98bn / base $123bn / bull $154bn EV (reportedly, per financial media coverage — not independently verified against a primary GS research note). Jefferies: $136-180bn EV (varies by note date; $180bn cited Nov 2025 is independently corroborated by Reuters/Business Standard coverage of the same Jefferies estimate). JM Financial: ~$140bn equity / ~$153bn EV (reportedly). ICICI Securities: ~$148bn by FY27 (reportedly). Bankers reportedly pitching sponsors as wide as $130-170bn (Bloomberg, Nov 2025). This model's own Bear/Base/Bull of $96bn / $129bn / $169bn EV (see row above) is an independent triangulation built from FY26A actuals and the listed Bharti Airtel multiple — it is not a restatement of any single house view, and sits within the range of reported street estimates above.
