Workbook

Sheet Cover
B2: PE Target Screening — Enterprise Software & Cybersecurity
B3: A systematic screen for LBO-suitable, profitable mid-cap software businesses
B5: Universe: | C5: 6 listed enterprise software / cybersecurity companies, $1-10bn market cap
B6: Screen date: | C6: Late August 2026 (see per-company source comments for exact snapshot dates)
B7: Objective: | C7: Identify names that combine LBO-friendly fundamentals (margin, growth quality, leverage headroom) with an entry price that isn't already pricing in the story
B9: Why This Screen
B10: A cheap EV/EBITDA multiple alone is not a buy signal — it's often a warning label. This screen scores companies on five dimensions a sponsor actually underwrites (growth quality, margin, leverage headroom, valuation, and business-quality/stability), rather than ranking on valuation alone. The output is the same discipline that would have surfaced Qualys (QLYS) as the strongest LBO candidate in this universe — see the companion LBO model and investment thesis for the full underwrite.
B12: Screen Output (from Scoring & Ranking tab)
B13: Rank | C13: Company | D13: Composite Score | E13: EV/EBITDA | F13: Verdict
B14: 1 | C14: =INDEX('Scoring & Ranking'!$B$5:$B$10,MATCH(1,'Scoring & Ranking'!$J$5:$J$10,0)) -> Qualys (QLYS) | D14: =INDEX('Scoring & Ranking'!$H$5:$H$10,MATCH(1,'Scoring & Ranking'!$J$5:$J$10,0)) -> 82.404534 | E14: =INDEX('Scoring & Ranking'!$L$5:$L$10,MATCH(1,'Scoring & Ranking'!$J$5:$J$10,0)) -> 7.3962987 | F14: =INDEX('Scoring & Ranking'!$K$5:$K$10,MATCH(1,'Scoring & Ranking'!$J$5:$J$10,0)) -> Top candidate
B15: 2 | C15: =INDEX('Scoring & Ranking'!$B$5:$B$10,MATCH(2,'Scoring & Ranking'!$J$5:$J$10,0)) -> Tenable (TENB) | D15: =INDEX('Scoring & Ranking'!$H$5:$H$10,MATCH(2,'Scoring & Ranking'!$J$5:$J$10,0)) -> 67.312955 | E15: =INDEX('Scoring & Ranking'!$L$5:$L$10,MATCH(2,'Scoring & Ranking'!$J$5:$J$10,0)) -> 10.071942 | F15: =INDEX('Scoring & Ranking'!$K$5:$K$10,MATCH(2,'Scoring & Ranking'!$J$5:$J$10,0)) -> Attractive
B16: 3 | C16: =INDEX('Scoring & Ranking'!$B$5:$B$10,MATCH(3,'Scoring & Ranking'!$J$5:$J$10,0)) -> ACI Worldwide (ACIW) | D16: =INDEX('Scoring & Ranking'!$H$5:$H$10,MATCH(3,'Scoring & Ranking'!$J$5:$J$10,0)) -> 56.623827 | E16: =INDEX('Scoring & Ranking'!$L$5:$L$10,MATCH(3,'Scoring & Ranking'!$J$5:$J$10,0)) -> 11.338333 | F16: =INDEX('Scoring & Ranking'!$K$5:$K$10,MATCH(3,'Scoring & Ranking'!$J$5:$J$10,0)) -> Priced in / pass
B17: 4 | C17: =INDEX('Scoring & Ranking'!$B$5:$B$10,MATCH(4,'Scoring & Ranking'!$J$5:$J$10,0)) -> Progress Software (PRGS) | D17: =INDEX('Scoring & Ranking'!$H$5:$H$10,MATCH(4,'Scoring & Ranking'!$J$5:$J$10,0)) -> 52.419286 | E17: =INDEX('Scoring & Ranking'!$L$5:$L$10,MATCH(4,'Scoring & Ranking'!$J$5:$J$10,0)) -> 6.8058824 | F17: =INDEX('Scoring & Ranking'!$K$5:$K$10,MATCH(4,'Scoring & Ranking'!$J$5:$J$10,0)) -> Priced in / pass
B18: 5 | C18: =INDEX('Scoring & Ranking'!$B$5:$B$10,MATCH(5,'Scoring & Ranking'!$J$5:$J$10,0)) -> Varonis (VRNS) | D18: =INDEX('Scoring & Ranking'!$H$5:$H$10,MATCH(5,'Scoring & Ranking'!$J$5:$J$10,0)) -> 43.085595 | E18: =INDEX('Scoring & Ranking'!$L$5:$L$10,MATCH(5,'Scoring & Ranking'!$J$5:$J$10,0)) -> 72.686441 | F18: =INDEX('Scoring & Ranking'!$K$5:$K$10,MATCH(5,'Scoring & Ranking'!$J$5:$J$10,0)) -> Fails quality/margin gate
B19: 6 | C19: =INDEX('Scoring & Ranking'!$B$5:$B$10,MATCH(6,'Scoring & Ranking'!$J$5:$J$10,0)) -> Rapid7 (RPD) | D19: =INDEX('Scoring & Ranking'!$H$5:$H$10,MATCH(6,'Scoring & Ranking'!$J$5:$J$10,0)) -> 28.634121 | E19: =INDEX('Scoring & Ranking'!$L$5:$L$10,MATCH(6,'Scoring & Ranking'!$J$5:$J$10,0)) -> N/M | F19: =INDEX('Scoring & Ranking'!$K$5:$K$10,MATCH(6,'Scoring & Ranking'!$J$5:$J$10,0)) -> Fails quality/margin gate
B22: This is an independent, illustrative screen built for portfolio/interview demonstration purposes, using public market data as of the dates noted in each company's source comment. It is not investment advice and is not exhaustive of the LBO-suitable software universe.

Sheet Screening Criteria
B2: Screening Criteria & Methodology
B4: A. Hard Gates (pass/fail — fails are flagged, not deleted)
B5: Criterion | C5: Threshold | D5: Rationale
B6: Minimum revenue scale | C6: 200 | D6: Too small for institutional LBO financing / thin lender universe below this.
B7: Maximum revenue scale | C7: 3000 | D7: Needs a club/consortium deal above this — outside single-sponsor sweet spot.
B8: Minimum EBITDA margin | C8: 0.15 | D8: FCF too thin to service meaningful LBO leverage below this.
B9: Maximum current net leverage | C9: 3.5 | D9: Little headroom to add debt — balance sheet already used.
B10: Maximum EV/EBITDA (not already priced for perfection) | C10: 15 | D10: Growth-equity multiple, not a buyout multiple — re-rating already happened.
B12: B. Composite Score Weights (0-100 scale per factor, weighted average)
B13: Factor | C13: Weight | D13: What it rewards
B14: EBITDA margin | C14: 0.25 | D14: Best predictor of how much leverage a business can service.
B15: Revenue growth quality | C15: 0.2 | D15: Sweet spot 5-15%: enough to grow into leverage, not so hot it demands a growth multiple.
B16: Leverage headroom | C16: 0.2 | D16: Lower current leverage = more room to add debt at entry.
B17: Valuation (EV/EBITDA) | C17: 0.2 | D17: Cheaper entry multiple, scored relative to the peer set.
B18: Business quality / stability | C18: 0.15 | D18: Qualitative: management continuity, activist noise, margin trajectory.
B19: Total | C19: =SUM(C14:C18) -> 1
B21: Gates flag rather than delete: a name failing a gate (e.g. RPD's thin margin/quality) stays in the universe with a visible red flag on the Scoring tab, because seeing WHY a statistically cheap name fails the screen is itself the useful output for a sourcing analyst.

Sheet Company Data
B2: Screening Universe — Raw Financial & Market Data
B4: ($mm unless noted) | C4: Qualys (QLYS) | D4: Tenable (TENB) | E4: ACI Worldwide (ACIW) | F4: Progress Software (PRGS) | G4: Rapid7 (RPD) | H4: Varonis (VRNS)
B5: Revenue (FY26E/TTM) | C5: 669.1 | D5: 1070 | E5: 1895 | F5: 994 | G5: 839 | H5: 737
B6: Revenue growth, % YoY | C6: 0.1 | D6: 0.09 | E6: 0.08 | F6: 0.04 | G6: 0.02 | H6: 0.175
B7: EBITDA (FY26E/TTM) | C7: 313.4 | D7: 278 | E7: 540 | F7: 425 | G7: 82.5 | H7: 59
B8: EBITDA Margin | C8: =C7/C5 -> 0.46839038 | D8: =D7/D5 -> 0.25981308 | E8: =E7/E5 -> 0.28496042 | F8: =F7/F5 -> 0.42756539 | G8: =G7/G5 -> 0.098331347 | H8: =H7/H5 -> 0.080054274
B9: Market Capitalization | C9: 2763.9 | D9: 3400 | E9: 5370 | F9: 1660 | G9: 770 | H9: 5200
B10: Net Debt / (Net Cash) | C10: -445.9 | D10: -600 | E10: 752.7 | F10: 1232.5 | G10: NA | H10: -911.5
B11: Enterprise Value | C11: =C9+C10 -> 2318 | D11: =D9+D10 -> 2800 | E11: =E9+E10 -> 6122.7 | F11: =F9+F10 -> 2892.5 | G11: NA | H11: =H9+H10 -> 4288.5
B12: EV / EBITDA | C12: =C11/C7 -> 7.3962987 | D12: =D11/D7 -> 10.071942 | E12: =E11/E7 -> 11.338333 | F12: =F11/F7 -> 6.8058824 | G12: N/M | H12: =H11/H7 -> 72.686441
B13: Net Leverage (Net Debt/EBITDA) | C13: =C10/C7 -> -1.4227824 | D13: =D10/D7 -> -2.1582734 | E13: =E10/E7 -> 1.3938889 | F13: =F10/F7 -> 2.9 | G13: N/A | H13: =H10/H7 -> -15.449153
B15: Rapid7 (RPD) is included deliberately as a stress-test case: statistically cheap on TTM EV/EBITDA in isolation, but capital structure and forward earnings are unusually hard to pin down amid activist involvement and a CEO transition in 2026 — exactly the kind of name a naive “cheapest multiple” screen would over-rate. All figures approximate, sourced from public market data providers (StockAnalysis, MacroTrends, GuruFocus, SimplyWall.st, company earnings releases/8-Ks) as of the dates noted in cell comments; treat as directional for a screening exercise, not deal-ready diligence.

Sheet Scoring & Ranking
B2: Scoring & Ranking Engine
B4: Company | C4: Margin Score | D4: Growth Score | E4: Leverage Score | F4: Valuation Score | G4: Quality Score (input) | H4: Composite Score | I4: Gate Check | J4: Rank | K4: Verdict | L4: EV/EBITDA (ref.)
B5: Qualys (QLYS) | C5: =MIN(100,MAX(0,'Company Data'!C8/0.6*100)) -> 78.065063 | D5: =MAX(0,100-ABS('Company Data'!C6-0.1)/0.15*100) -> 100 | E5: =MAX(0,MIN(100,100*(1-'Company Data'!C13/'Screening Criteria'!$C$9))) -> 100 | F5: =MAX(0,MIN(100,100*(1-'Company Data'!C12/'Screening Criteria'!$C$10))) -> 50.691342 | G5: 85 | H5: =C5*'Screening Criteria'!$C$14+D5*'Screening Criteria'!$C$15+E5*'Screening Criteria'!$C$16+F5*'Screening Criteria'!$C$17+G5*'Screening Criteria'!$C$18 -> 82.404534 | I5: =IF(AND('Company Data'!C5>='Screening Criteria'!$C$6,'Company Data'!C5<='Screening Criteria'!$C$7,'Company Data'!C8>='Screening Criteria'!$C$8),"PASS","FLAG") -> PASS | J5: =RANK(H5,$H$5:$H$10) -> 1 | K5: =IF(I5="FLAG","Fails quality/margin gate",IF(J5=1,"Top candidate",IF(H5>=60,"Attractive","Priced in / pass"))) -> Top candidate | L5: ='Company Data'!C12 -> 7.3962987
B6: Tenable (TENB) | C6: =MIN(100,MAX(0,'Company Data'!D8/0.6*100)) -> 43.302181 | D6: =MAX(0,100-ABS('Company Data'!D6-0.1)/0.15*100) -> 93.333333 | E6: =MAX(0,MIN(100,100*(1-'Company Data'!D13/'Screening Criteria'!$C$9))) -> 100 | F6: =MAX(0,MIN(100,100*(1-'Company Data'!D12/'Screening Criteria'!$C$10))) -> 32.853717 | G6: 75 | H6: =C6*'Screening Criteria'!$C$14+D6*'Screening Criteria'!$C$15+E6*'Screening Criteria'!$C$16+F6*'Screening Criteria'!$C$17+G6*'Screening Criteria'!$C$18 -> 67.312955 | I6: =IF(AND('Company Data'!D5>='Screening Criteria'!$C$6,'Company Data'!D5<='Screening Criteria'!$C$7,'Company Data'!D8>='Screening Criteria'!$C$8),"PASS","FLAG") -> PASS | J6: =RANK(H6,$H$5:$H$10) -> 2 | K6: =IF(I6="FLAG","Fails quality/margin gate",IF(J6=1,"Top candidate",IF(H6>=60,"Attractive","Priced in / pass"))) -> Attractive | L6: ='Company Data'!D12 -> 10.071942
B7: ACI Worldwide (ACIW) | C7: =MIN(100,MAX(0,'Company Data'!E8/0.6*100)) -> 47.493404 | D7: =MAX(0,100-ABS('Company Data'!E6-0.1)/0.15*100) -> 86.666667 | E7: =MAX(0,MIN(100,100*(1-'Company Data'!E13/'Screening Criteria'!$C$9))) -> 60.174603 | F7: =MAX(0,MIN(100,100*(1-'Company Data'!E12/'Screening Criteria'!$C$10))) -> 24.411111 | G7: 70 | H7: =C7*'Screening Criteria'!$C$14+D7*'Screening Criteria'!$C$15+E7*'Screening Criteria'!$C$16+F7*'Screening Criteria'!$C$17+G7*'Screening Criteria'!$C$18 -> 56.623827 | I7: =IF(AND('Company Data'!E5>='Screening Criteria'!$C$6,'Company Data'!E5<='Screening Criteria'!$C$7,'Company Data'!E8>='Screening Criteria'!$C$8),"PASS","FLAG") -> PASS | J7: =RANK(H7,$H$5:$H$10) -> 3 | K7: =IF(I7="FLAG","Fails quality/margin gate",IF(J7=1,"Top candidate",IF(H7>=60,"Attractive","Priced in / pass"))) -> Priced in / pass | L7: ='Company Data'!E12 -> 11.338333
B8: Progress Software (PRGS) | C8: =MIN(100,MAX(0,'Company Data'!F8/0.6*100)) -> 71.260899 | D8: =MAX(0,100-ABS('Company Data'!F6-0.1)/0.15*100) -> 60 | E8: =MAX(0,MIN(100,100*(1-'Company Data'!F13/'Screening Criteria'!$C$9))) -> 17.142857 | F8: =MAX(0,MIN(100,100*(1-'Company Data'!F12/'Screening Criteria'!$C$10))) -> 54.627451 | G8: 55 | H8: =C8*'Screening Criteria'!$C$14+D8*'Screening Criteria'!$C$15+E8*'Screening Criteria'!$C$16+F8*'Screening Criteria'!$C$17+G8*'Screening Criteria'!$C$18 -> 52.419286 | I8: =IF(AND('Company Data'!F5>='Screening Criteria'!$C$6,'Company Data'!F5<='Screening Criteria'!$C$7,'Company Data'!F8>='Screening Criteria'!$C$8),"PASS","FLAG") -> PASS | J8: =RANK(H8,$H$5:$H$10) -> 4 | K8: =IF(I8="FLAG","Fails quality/margin gate",IF(J8=1,"Top candidate",IF(H8>=60,"Attractive","Priced in / pass"))) -> Priced in / pass | L8: ='Company Data'!F12 -> 6.8058824
B9: Rapid7 (RPD) | C9: =MIN(100,MAX(0,'Company Data'!G8/0.6*100)) -> 16.388558 | D9: =MAX(0,100-ABS('Company Data'!G6-0.1)/0.15*100) -> 46.666667 | E9: N/A | F9: N/A | G9: 25 | H9: =(C9*'Screening Criteria'!$C$14+D9*'Screening Criteria'!$C$15+G9*'Screening Criteria'!$C$18)/('Screening Criteria'!$C$14+'Screening Criteria'!$C$15+'Screening Criteria'!$C$18) -> 28.634121 | I9: =IF(AND('Company Data'!G5>='Screening Criteria'!$C$6,'Company Data'!G5<='Screening Criteria'!$C$7,'Company Data'!G8>='Screening Criteria'!$C$8),"PASS","FLAG") -> FLAG | J9: =RANK(H9,$H$5:$H$10) -> 6 | K9: =IF(I9="FLAG","Fails quality/margin gate",IF(J9=1,"Top candidate",IF(H9>=60,"Attractive","Priced in / pass"))) -> Fails quality/margin gate | L9: ='Company Data'!G12 -> N/M
B10: Varonis (VRNS) | C10: =MIN(100,MAX(0,'Company Data'!H8/0.6*100)) -> 13.342379 | D10: =MAX(0,100-ABS('Company Data'!H6-0.1)/0.15*100) -> 50 | E10: =MAX(0,MIN(100,100*(1-'Company Data'!H13/'Screening Criteria'!$C$9))) -> 100 | F10: =MAX(0,MIN(100,100*(1-'Company Data'!H12/'Screening Criteria'!$C$10))) -> 0 | G10: 65 | H10: =C10*'Screening Criteria'!$C$14+D10*'Screening Criteria'!$C$15+E10*'Screening Criteria'!$C$16+F10*'Screening Criteria'!$C$17+G10*'Screening Criteria'!$C$18 -> 43.085595 | I10: =IF(AND('Company Data'!H5>='Screening Criteria'!$C$6,'Company Data'!H5<='Screening Criteria'!$C$7,'Company Data'!H8>='Screening Criteria'!$C$8),"PASS","FLAG") -> FLAG | J10: =RANK(H10,$H$5:$H$10) -> 5 | K10: =IF(I10="FLAG","Fails quality/margin gate",IF(J10=1,"Top candidate",IF(H10>=60,"Attractive","Priced in / pass"))) -> Fails quality/margin gate | L10: ='Company Data'!H12 -> 72.686441
